spotify_playlist_utility/Spotify.py
spotify_playlist_utility/Track.py
spotify_playlist_utility/TrackLists.py
spotify_playlist_utility/__init__.py
spotify_playlist_utility/__main__.py
spotify_playlist_utility-0.0.3.dist-info/LICENSE.txt
spotify_playlist_utility-0.0.3.dist-info/METADATA
spotify_playlist_utility-0.0.3.dist-info/WHEEL
spotify_playlist_utility-0.0.3.dist-info/entry_points.txt
spotify_playlist_utility-0.0.3.dist-info/top_level.txt
spotify_playlist_utility-0.0.3.dist-info/RECORD
