Metadata-Version: 2.1
Name: spotify-playlist-utility
Version: 0.0.3
Summary: Python utility to manipulate, and report on, Spotify playlists.
Home-page: https://github.com/ryanwarrick/spotify-playlist-utility
Author: Ryan Warrick
Author-email: ryanwarrick1@gmail.com
License: UNKNOWN
Platform: UNKNOWN
Classifier: Programming Language :: Python :: 3
Classifier: License :: OSI Approved :: GNU Affero General Public License v3 or later (AGPLv3+)
Classifier: Operating System :: OS Independent
Classifier: Natural Language :: English
Requires-Python: >=3.6
License-File: LICENSE.txt
Requires-Dist: spotipy
Requires-Dist: requests
